sknetwork/__init__.py
sknetwork/sknetwork.py
sknetwork/linkpred/base.py
sknetwork/linkpred/__init__.py
sknetwork/linkpred/first_order_core.cpython-37m-x86_64-linux-gnu.so
sknetwork/linkpred/first_order.py
sknetwork/linkpred/postprocessing.py
sknetwork/linkpred/tests/test_API.py
sknetwork/linkpred/tests/__init__.py
sknetwork/linkpred/tests/test_postprocessing.py
sknetwork/clustering/kmeans.py
sknetwork/clustering/base.py
sknetwork/clustering/__init__.py
sknetwork/clustering/propagation_clustering.py
sknetwork/clustering/postprocess.py
sknetwork/clustering/metrics.py
sknetwork/clustering/louvain.py
sknetwork/clustering/louvain_core.cpython-37m-x86_64-linux-gnu.so
sknetwork/clustering/tests/test_API.py
sknetwork/clustering/tests/test_metrics.py
sknetwork/clustering/tests/__init__.py
sknetwork/clustering/tests/test_louvain.py
sknetwork/clustering/tests/test_kmeans.py
sknetwork/clustering/tests/test_post_processing.py
sknetwork/linalg/normalization.py
sknetwork/linalg/diteration.cpython-37m-x86_64-linux-gnu.so
sknetwork/linalg/eig_solver.py
sknetwork/linalg/ppr_solver.py
sknetwork/linalg/sparse_lowrank.py
sknetwork/linalg/operators.py
sknetwork/linalg/randomized_methods.py
sknetwork/linalg/__init__.py
sknetwork/linalg/basics.py
sknetwork/linalg/auto_mode.py
sknetwork/linalg/polynome.py
sknetwork/linalg/svd_solver.py
sknetwork/linalg/tests/test_ppr.py
sknetwork/linalg/tests/test_operators.py
sknetwork/linalg/tests/test_polynome.py
sknetwork/linalg/tests/__init__.py
sknetwork/linalg/tests/test_randomized_methods.py
sknetwork/linalg/tests/test_eig.py
sknetwork/linalg/tests/test_sparse_lowrank.py
sknetwork/linalg/tests/test_svd.py
sknetwork/linalg/tests/test_normalization.py
sknetwork/classification/base.py
sknetwork/classification/diffusion.py
sknetwork/classification/__init__.py
sknetwork/classification/knn.py
sknetwork/classification/metrics.py
sknetwork/classification/vote.cpython-37m-x86_64-linux-gnu.so
scikit_network_dbda093-0.20.0b0.dist-info/top_level.txt
scikit_network_dbda093-0.20.0b0.dist-info/AUTHORS.rst
scikit_network_dbda093-0.20.0b0.dist-info/entry_points.txt
scikit_network_dbda093-0.20.0b0.dist-info/LICENSE
scikit_network_dbda093-0.20.0b0.dist-info/WHEEL
scikit_network_dbda093-0.20.0b0.dist-info/METADATA
scikit_network_dbda093-0.20.0b0.dist-info/RECORD
