Metadata-Version: 2.1
Name: scikit-network-dbda093
Version: 0.20.0b0
Summary: Graph algorithms
Home-page: https://github.com/altana-tech/scikit-network
Author: Scikit-network team
Author-email: bonald@enst.fr
License: BSD license
Keywords: sknetwork
Platform: UNKNOWN
Classifier: Development Status :: 2 - Pre-Alpha
Classifier: Intended Audience :: Developers
Classifier: License :: OSI Approved :: BSD License
Classifier: Natural Language :: English
Classifier: Programming Language :: Python :: 3.6
Classifier: Programming Language :: Python :: 3.7
Classifier: Programming Language :: Python :: 3.8
Requires-Dist: numpy (>=1.18.3)
Requires-Dist: scipy (>=1.4.1)
